alist_sdk/__init__.py
alist_sdk/__main__.py
alist_sdk/alistpath.py
alist_sdk/async_client.py
alist_sdk/client.py
alist_sdk/err.py
alist_sdk/models.py
alist_sdk/path_lib.py
alist_sdk/py312_pathlib.py
alist_sdk/verify.py
alist_sdk/version.py
alist_sdk/cmd/__init__.py
alist_sdk/cmd/admin.py
alist_sdk/cmd/app.py
alist_sdk/cmd/auth.py
alist_sdk/cmd/base.py
alist_sdk/cmd/fs.py
alist_sdk/tools/__init__.py
alist_sdk/tools/client.py
alist_sdk/tools/configs.py
alist_sdk/tools/models.py
alist_sdk-0.37.15.dist-info/METADATA
alist_sdk-0.37.15.dist-info/WHEEL
alist_sdk-0.37.15.dist-info/entry_points.txt
alist_sdk-0.37.15.dist-info/top_level.txt
alist_sdk-0.37.15.dist-info/RECORD
